__init__.py
__main__.py
turtlebyte.py
turtlebyte-0.2.0.dist-info/licenses/LICENSE
utils/__init__.py
utils/detection.py
utils/normalize.py
turtlebyte-0.2.0.dist-info/METADATA
turtlebyte-0.2.0.dist-info/WHEEL
turtlebyte-0.2.0.dist-info/top_level.txt
turtlebyte-0.2.0.dist-info/RECORD
