Metadata-Version: 2.4
Name: turtlebyte
Version: 0.2.0
Summary: A virtual memory device drawn by python's turtle
Author-email: isaac1000000 <isaac.fisher@nyu.edu>
License: MIT License
Project-URL: Homepage, https://github.com/isaac1000000/turtlebyte
Project-URL: Repository, https://github.com/isaac1000000/turtlebyte
Keywords: python,turtle,HDD,memory,fun
Classifier: Programming Language :: Python :: 3
Requires-Python: >=3.7
License-File: LICENSE
Dynamic: license-file
